{"nodes": [{"id": "users_alexander_documents_task_packages_ui_src_atoms_mgallery_mgallery_mdx", "label": "MGallery.mdx", "file_type": "document", "source_file": "packages/ui/src/atoms/MGallery/MGallery.mdx", "source_location": "L1"}, {"id": "mgallery_mgallery_definition", "label": "Definition", "file_type": "document", "source_file": "packages/ui/src/atoms/MGallery/MGallery.mdx", "source_location": "L7"}, {"id": "mgallery_mgallery_customization", "label": "Customization", "file_type": "document", "source_file": "packages/ui/src/atoms/MGallery/MGallery.mdx", "source_location": "L17"}], "edges": [{"source": "users_alexander_documents_task_packages_ui_src_atoms_mgallery_mgallery_mdx", "target": "mgallery_mgallery_definition", "relation": "contains", "confidence": "EXTRACTED", "source_file": "packages/ui/src/atoms/MGallery/MGallery.mdx", "source_location": "L7", "weight": 1.0}, {"source": "mgallery_mgallery_definition", "target": "mgallery_mgallery_customization", "relation": "contains", "confidence": "EXTRACTED", "source_file": "packages/ui/src/atoms/MGallery/MGallery.mdx", "source_location": "L17", "weight": 1.0}], "input_tokens": 0, "output_tokens": 0}